aliyunsdkeci/__init__.py
aliyunsdkeci/request/__init__.py
aliyunsdkeci/request/v20180808/CreateContainerGroupRequest.py
aliyunsdkeci/request/v20180808/CreateImageCacheRequest.py
aliyunsdkeci/request/v20180808/DeleteContainerGroupRequest.py
aliyunsdkeci/request/v20180808/DeleteImageCacheRequest.py
aliyunsdkeci/request/v20180808/DescribeContainerGroupMetricRequest.py
aliyunsdkeci/request/v20180808/DescribeContainerGroupPriceRequest.py
aliyunsdkeci/request/v20180808/DescribeContainerGroupsRequest.py
aliyunsdkeci/request/v20180808/DescribeContainerLogRequest.py
aliyunsdkeci/request/v20180808/DescribeImageCachesRequest.py
aliyunsdkeci/request/v20180808/DescribeMultiContainerGroupMetricRequest.py
aliyunsdkeci/request/v20180808/DescribeRegionsRequest.py
aliyunsdkeci/request/v20180808/ExecContainerCommandRequest.py
aliyunsdkeci/request/v20180808/ListUsageRequest.py
aliyunsdkeci/request/v20180808/RestartContainerGroupRequest.py
aliyunsdkeci/request/v20180808/UpdateContainerGroupRequest.py
aliyunsdkeci/request/v20180808/__init__.py
aliyunsdkeci-1.1.9.dist-info/METADATA
aliyunsdkeci-1.1.9.dist-info/WHEEL
aliyunsdkeci-1.1.9.dist-info/top_level.txt
aliyunsdkeci-1.1.9.dist-info/RECORD
